<?xml version="1.0" encoding="UTF-8"?>
<!DOCTYPE nmaprun>
<?xml-stylesheet href="file:///usr/bin/../share/nmap/nmap.xsl" type="text/xsl"?>
<!-- Nmap 7.40 scan initiated Thu Sep 19 14:45:44 2019 as: nmap -p 80,443 -A -oA testfile www.zencurity.com -->
<nmaprun scanner="nmap" args="nmap -p 80,443 -A -oA testfile www.zencurity.com" start="1568897144" startstr="Thu Sep 19 14:45:44 2019" version="7.40" xmloutputversion="1.04">
<scaninfo type="syn" protocol="tcp" numservices="2" services="80,443"/>
<verbose level="0"/>
<debugging level="0"/>
<host starttime="1568897145" endtime="1568897166"><status state="up" reason="syn-ack" reason_ttl="50"/>
<address addr="185.129.60.130" addrtype="ipv4"/>
<hostnames>
<hostname name="www.zencurity.com" type="user"/>
</hostnames>
<ports><port protocol="tcp" portid="80"><state state="open" reason="syn-ack" reason_ttl="50"/><service name="http" product="nginx" method="probed" conf="10"><cpe>cpe:/a:igor_sysoev:nginx</cpe></service><script id="http-server-header" output="nginx"><elem>nginx</elem>
</script><script id="http-title" output="Did not follow redirect to https://www.zencurity.com/"><elem key="redirect_url">https://www.zencurity.com/</elem>
</script></port>
<port protocol="tcp" portid="443"><state state="open" reason="syn-ack" reason_ttl="50"/><service name="http" product="nginx" tunnel="ssl" method="probed" conf="10"><cpe>cpe:/a:igor_sysoev:nginx</cpe></service><script id="http-server-header" output="nginx"><elem>nginx</elem>
</script><script id="http-title" output="Home Page"><elem key="title">Home Page</elem>
</script><script id="ssl-cert" output="Subject: commonName=zencurity.com&#xa;Subject Alternative Name: DNS:www.zencurity.com, DNS:www.zencurity.dk, DNS:zencurity.com, DNS:zencurity.dk&#xa;Not valid before: 2019-08-29T18:58:41&#xa;Not valid after:  2019-11-27T18:58:41"><table key="subject">
<elem key="commonName">zencurity.com</elem>
</table>
<table key="issuer">
<elem key="commonName">Let&apos;s Encrypt Authority X3</elem>
<elem key="countryName">US</elem>
<elem key="organizationName">Let&apos;s Encrypt</elem>
</table>
<table key="pubkey">
<elem key="bits">4096</elem>
<elem key="exponent">userdata: 0x5cc4ed854e18</elem>
<elem key="type">rsa</elem>
</table>
<table key="extensions">
<table>
<elem key="name">X509v3 Key Usage</elem>
<elem key="value">Digital Signature, Key Encipherment</elem>
<elem key="critical">true</elem>
</table>
<table>
<elem key="value">TLS Web Server Authentication, TLS Web Client Authentication</elem>
<elem key="name">X509v3 Extended Key Usage</elem>
</table>
<table>
<elem key="name">X509v3 Basic Constraints</elem>
<elem key="value">CA:FALSE</elem>
<elem key="critical">true</elem>
</table>
<table>
<elem key="value">F7:70:E3:17:32:AC:AE:59:D0:00:C9:41:E9:FE:3B:C8:7F:81:E5:EE</elem>
<elem key="name">X509v3 Subject Key Identifier</elem>
</table>
<table>
<elem key="value">keyid:A8:4A:6A:63:04:7D:DD:BA:E6:D1:39:B7:A6:45:65:EF:F3:A8:EC:A1&#xa;</elem>
<elem key="name">X509v3 Authority Key Identifier</elem>
</table>
<table>
<elem key="value">OCSP - URI:http://ocsp.int-x3.letsencrypt.org&#xa;CA Issuers - URI:http://cert.int-x3.letsencrypt.org/&#xa;</elem>
<elem key="name">Authority Information Access</elem>
</table>
<table>
<elem key="value">DNS:www.zencurity.com, DNS:www.zencurity.dk, DNS:zencurity.com, DNS:zencurity.dk</elem>
<elem key="name">X509v3 Subject Alternative Name</elem>
</table>
<table>
<elem key="value">Policy: 2.23.140.1.2.1&#xa;Policy: 1.3.6.1.4.1.44947.1.1.1&#xa;  CPS: http://cps.letsencrypt.org&#xa;</elem>
<elem key="name">X509v3 Certificate Policies</elem>
</table>
<table>
<elem key="value">Signed Certificate Timestamp:&#xa;    Version   : v1 (0x0)&#xa;    Log ID    : E2:69:4B:AE:26:E8:E9:40:09:E8:86:1B:B6:3B:83:D4:&#xa;                3E:E7:FE:74:88:FB:A4:8F:28:93:01:9D:DD:F1:DB:FE&#xa;    Timestamp : Aug 29 19:58:41.398 2019 GMT&#xa;    Extensions: none&#xa;    Signature : ecdsa-with-SHA256&#xa;                30:45:02:20:60:22:5A:42:FE:DC:25:E0:49:55:60:FC:&#xa;                10:E9:0C:0D:C7:3A:DC:6F:8B:36:C3:0B:C8:D7:A9:12:&#xa;                AC:DB:3E:67:02:21:00:D0:B2:5B:F6:A0:37:0D:6B:AA:&#xa;                89:DA:D5:FB:3F:17:83:B7:7E:B6:9F:31:B7:D3:E3:20:&#xa;                6D:FA:D5:1D:51:83:37&#xa;Signed Certificate Timestamp:&#xa;    Version   : v1 (0x0)&#xa;    Log ID    : 63:F2:DB:CD:E8:3B:CC:2C:CF:0B:72:84:27:57:6B:33:&#xa;                A4:8D:61:77:8F:BD:75:A6:38:B1:C7:68:54:4B:D8:8D&#xa;    Timestamp : Aug 29 19:58:41.399 2019 GMT&#xa;    Extensions: none&#xa;    Signature : ecdsa-with-SHA256&#xa;                30:45:02:20:32:2A:90:C7:E7:B6:C9:16:90:0D:EA:AA:&#xa;                30:6D:7E:F1:E9:31:8A:31:53:14:70:F8:BB:69:1F:02:&#xa;                48:78:04:DE:02:21:00:DD:46:04:95:F9:60:B7:18:30:&#xa;                FB:26:F3:6F:54:14:93:64:79:EE:97:49:EC:1A:CE:84:&#xa;                A0:88:69:24:63:98:C2</elem>
<elem key="name">CT Precertificate SCTs</elem>
</table>
</table>
<elem key="sig_algo">sha256WithRSAEncryption</elem>
<table key="validity">
<elem key="notAfter">2019-11-27T18:58:41</elem>
<elem key="notBefore">2019-08-29T18:58:41</elem>
</table>
<elem key="md5">331bed80b5173fa08bd25f5664bbd7ca</elem>
<elem key="sha1">374adeed59d685b2033c1535a102b4196b450a2b</elem>
<elem key="pem">-&#45;&#45;&#45;&#45;BEGIN CERTIFICATE-&#45;&#45;&#45;&#45;&#xa;MIIGhTCCBW2gAwIBAgISA0H5uKdj6py0GP5zKvhkndusMA0GCSqGSIb3DQEBCwUA&#xa;MEoxCzAJBgNVBAYTAlVTMRYwFAYDVQQKEw1MZXQncyBFbmNyeXB0MSMwIQYDVQQD&#xa;ExpMZXQncyBFbmNyeXB0IEF1dGhvcml0eSBYMzAeFw0xOTA4MjkxODU4NDFaFw0x&#xa;OTExMjcxODU4NDFaMBgxFjAUBgNVBAMTDXplbmN1cml0eS5jb20wggIiMA0GCSqG&#xa;SIb3DQEBAQUAA4ICDwAwggIKAoICAQDw370NIdIagH/NDlGY9Z7VEV/gEzkI7Ys/&#xa;rvyMvjoAm17Vw4CVlwbzfHAmYtxJvkDwrSQojQsPayn9FiOmzk57CEX5haK3WQg+&#xa;ehsAXLxWb8L+a3+8j0vBNs0+oXGxjqVbjgVJHZORoCEje7/nkf0LlPYpYF/UWNZM&#xa;PX1h/M03cXalEFk9YXq0lh1Z8oGBRitSb0YXoz1LhhTzM5ZpveAQrwp9sessqkp7&#xa;3lXB74/lc6JvDwysjzpsIM3lH7uJbhWkQpjfGsH7IFSQvmDoNnRfNlw2Cc9DFfBH&#xa;DJlZVZyHTPCxfDv3EVl22Xt6Eew+OlHprAF8G1gqgg03A2nm+XItlDg7t3cs5cg+&#xa;Fj8a7iv3a6V4NnMPIwpw0UU/pi/XymxkP/MxknRIsdGpjXcUGvPHbk1SDyG8caPP&#xa;GS5J0BgxEksK/21YQ00fGKh+gXb51qLzeXdtrsoTCELKsUriGILgDy4AzNboC/Cm&#xa;fJ0JKYlQIWMcrc7HyuKtiOPTiBECG2aCx6tbbYtIpuPBs5DzAUNjAiLtQP3frcWu&#xa;VMkXDpbyAkKgqwbhP6N+D3tMLWmN521ADSE5eejgP4W6jfx9mk9QC8gA+KrZsfGG&#xa;9spec/s3uE4Dfvx+8ydcpLwgnt6EE9+5ZjPrIBtyEHP/L1uvsF/Becl34agdP9Au&#xa;m2bZSQDpHwIDAQABo4IClTCCApEwDgYDVR0PAQH/BAQDAgWgMB0GA1UdJQQWMBQG&#xa;CCsGAQUFBwMBBggrBgEFBQcDAjAMBgNVHRMBAf8EAjAAMB0GA1UdDgQWBBT3cOMX&#xa;MqyuWdAAyUHp/jvIf4Hl7jAfBgNVHSMEGDAWgBSoSmpjBH3duubRObemRWXv86js&#xa;oTBvBggrBgEFBQcBAQRjMGEwLgYIKwYBBQUHMAGGImh0dHA6Ly9vY3NwLmludC14&#xa;My5sZXRzZW5jcnlwdC5vcmcwLwYIKwYBBQUHMAKGI2h0dHA6Ly9jZXJ0LmludC14&#xa;My5sZXRzZW5jcnlwdC5vcmcvMEsGA1UdEQREMEKCEXd3dy56ZW5jdXJpdHkuY29t&#xa;ghB3d3cuemVuY3VyaXR5LmRrgg16ZW5jdXJpdHkuY29tggx6ZW5jdXJpdHkuZGsw&#xa;TAYDVR0gBEUwQzAIBgZngQwBAgEwNwYLKwYBBAGC3xMBAQEwKDAmBggrBgEFBQcC&#xa;ARYaaHR0cDovL2Nwcy5sZXRzZW5jcnlwdC5vcmcwggEEBgorBgEEAdZ5AgQCBIH1&#xa;BIHyAPAAdgDiaUuuJujpQAnohhu2O4PUPuf+dIj7pI8okwGd3fHb/gAAAWze9Wr2&#xa;AAAEAwBHMEUCIGAiWkL+3CXgSVVg/BDpDA3HOtxvizbDC8jXqRKs2z5nAiEA0LJb&#xa;9qA3DWuqidrV+z8Xg7d+tp8xt9PjIG361R1RgzcAdgBj8tvN6DvMLM8LcoQnV2sz&#xa;pI1hd4+9daY4scdoVEvYjQAAAWze9Wr3AAAEAwBHMEUCIDIqkMfntskWkA3qqjBt&#xa;fvHpMYoxUxRw+LtpHwJIeATeAiEA3UYElflgtxgw+ybzb1QUk2R57pdJ7BrOhKCI&#xa;aSRjmMIwDQYJKoZIhvcNAQELBQADggEBAI5La4zpngWT8pWxDh0jRfNMOk5VlvKD&#xa;tE2Z57R1ELF0r0ALA2oJL1BdsGFhlllQ/eTFXY7ZrcbgYDnKzHGp+RYgVDTW4QXN&#xa;aae0C9JeWaXHaq9XEfP24u4hSRzaF1SkMpc9aedYglpb5bQsnKiSAzXiGA+SBJ2D&#xa;S2JL3GHlDooNt6jRyvgr4zKFck5MFwJJHGBmqqdKlbpATevMMlq6F2Q2bMUb21Rg&#xa;MV5VN7v5314BxcDXcCKV2iWf5Z+ardz9mYDMwqlVBkSO4vBvs86rwUBdiKDu9vyJ&#xa;+JsooHYvnQ/fddz+JBFTUB0S3Yk5ckDLLXlJkVEtDEoVmfyy581KRe8=&#xa;-&#45;&#45;&#45;&#45;END CERTIFICATE-&#45;&#45;&#45;&#45;&#xa;</elem>
</script><script id="ssl-date" output="TLS randomness does not represent time"></script></port>
</ports>
<os><portused state="open" proto="tcp" portid="80"/>
<osmatch name="OpenBSD 4.0" accuracy="96" line="85254">
<osclass type="general purpose" vendor="OpenBSD" osfamily="OpenBSD" osgen="4.X" accuracy="96"><cpe>cpe:/o:openbsd:openbsd:4.0</cpe></osclass>
</osmatch>
<osmatch name="OpenBSD 4.1 - 4.3" accuracy="89" line="85383">
<osclass type="general purpose" vendor="OpenBSD" osfamily="OpenBSD" osgen="4.X" accuracy="89"><cpe>cpe:/o:openbsd:openbsd:4</cpe></osclass>
</osmatch>
<osmatch name="OpenBSD 5.3" accuracy="89" line="86160">
<osclass type="general purpose" vendor="OpenBSD" osfamily="OpenBSD" osgen="5.X" accuracy="89"><cpe>cpe:/o:openbsd:openbsd:5.3</cpe></osclass>
</osmatch>
<osmatch name="OpenBSD 4.3" accuracy="89" line="85510">
<osclass type="general purpose" vendor="OpenBSD" osfamily="OpenBSD" osgen="4.X" accuracy="89"><cpe>cpe:/o:openbsd:openbsd:4.3</cpe></osclass>
</osmatch>
<osmatch name="OpenBSD 5.0 - 5.4" accuracy="89" line="86048">
<osclass type="general purpose" vendor="OpenBSD" osfamily="OpenBSD" osgen="5.X" accuracy="89"><cpe>cpe:/o:openbsd:openbsd:5</cpe></osclass>
</osmatch>
<osmatch name="IronPort AsyncOS 7.5.1" accuracy="88" line="38169">
<osclass type="firewall" vendor="IronPort" osfamily="AsyncOS" osgen="7.X" accuracy="88"><cpe>cpe:/o:ironport:asyncos:7.5.1</cpe></osclass>
</osmatch>
<osmatch name="OpenBSD 4.6" accuracy="86" line="85891">
<osclass type="general purpose" vendor="OpenBSD" osfamily="OpenBSD" osgen="4.X" accuracy="86"><cpe>cpe:/o:openbsd:openbsd:4.6</cpe></osclass>
</osmatch>
</os>
<uptime seconds="6" lastboot="Thu Sep 19 14:46:00 2019"/>
<distance value="15"/>
<tcpsequence index="258" difficulty="Good luck!" values="61EB6AA1,2F2B1AFE,EE0550D0,61245A99,512E5B2,DB455DC7"/>
<ipidsequence class="Randomized" values="C582,AD59,C684,371F,208A,B253"/>
<tcptssequence class="other" values="512071ED,CA70E29E,BDF09A31,5304B70,EF4DFD33,7F1A12ED"/>
<trace port="443" proto="tcp">
<hop ttl="1" ipaddr="10.137.0.6" rtt="0.29"/>
<hop ttl="2" ipaddr="10.137.0.5" rtt="0.48"/>
<hop ttl="3" ipaddr="10.102.168.10" rtt="2.60"/>
<hop ttl="4" ipaddr="10.102.5.10" rtt="2.60"/>
<hop ttl="5" ipaddr="10.255.254.13" rtt="2.61"/>
<hop ttl="6" ipaddr="10.255.254.5" rtt="48.01"/>
<hop ttl="7" ipaddr="10.255.254.6" rtt="3.66"/>
<hop ttl="15" ipaddr="185.129.60.130" rtt="4.77"/>
</trace>
<times srtt="4966" rttvar="1066" to="100000"/>
</host>
<runstats><finished time="1568897166" timestr="Thu Sep 19 14:46:06 2019" elapsed="22.08" summary="Nmap done at Thu Sep 19 14:46:06 2019; 1 IP address (1 host up) scanned in 22.08 seconds" exit="success"/><hosts up="1" down="0" total="1"/>
</runstats>
</nmaprun>
